DCACP/__init__.py
DCACP-0.0.5.dist-info/LICENSE
DCACP-0.0.5.dist-info/METADATA
DCACP-0.0.5.dist-info/WHEEL
DCACP-0.0.5.dist-info/top_level.txt
DCACP-0.0.5.dist-info/RECORD
